{
  "season": "2025-2026",
  "source": "Swim Ontario",
  "course_type": "25m",
  "gender": "female",
  "standards": {
    "OSC": {
      "name": "Ontario Swimming Championships (SC)",
      "description": "Ontario Swimming Championships qualifying times - Short Course"
    },
    "OAG": {
      "name": "Ontario Age Group (SC)",
      "description": "Ontario Age Group qualifying times - Short Course"
    }
  },
  "age_groups": ["11U", "12", "13U", "14", "15", "16", "17O"],
  "times": {
    "50FR": {
      "11U": { "OSC": "0:31.38", "OAG": "0:32.16" },
      "12":  { "OSC": "0:29.86", "OAG": "0:30.61" },
      "13U": { "OSC": "0:28.35", "OAG": "0:29.06" },
      "14":  { "OSC": "0:28.07", "OAG": "0:28.77" },
      "15":  { "OSC": "0:27.70", "OAG": "0:28.39" },
      "16":  { "OSC": "0:27.42", "OAG": "0:28.11" },
      "17O": { "OSC": "0:27.15", "OAG": "0:27.83" }
    },
    "100FR": {
      "11U": { "OSC": "1:09.09", "OAG": "1:10.82" },
      "12":  { "OSC": "1:05.58", "OAG": "1:07.22" },
      "13U": { "OSC": "1:01.88", "OAG": "1:03.43" },
      "14":  { "OSC": "1:01.09", "OAG": "1:02.62" },
      "15":  { "OSC": "1:00.30", "OAG": "1:01.81" },
      "16":  { "OSC": "0:59.30", "OAG": "1:00.78" },
      "17O": { "OSC": "0:58.72", "OAG": "1:00.19" }
    },
    "200FR": {
      "11U": { "OSC": "2:29.56", "OAG": "2:33.30" },
      "12":  { "OSC": "2:24.14", "OAG": "2:27.74" },
      "13U": { "OSC": "2:14.92", "OAG": "2:18.29" },
      "14":  { "OSC": "2:13.57", "OAG": "2:16.91" },
      "15":  { "OSC": "2:12.24", "OAG": "2:15.55" },
      "16":  { "OSC": "2:10.67", "OAG": "2:13.94" },
      "17O": { "OSC": "2:09.36", "OAG": "2:12.59" }
    },
    "400FR": {
      "11U": { "OSC": "5:14.38", "OAG": "5:22.24" },
      "12":  { "OSC": "5:02.94", "OAG": "5:10.51" },
      "13U": { "OSC": "4:41.50", "OAG": "4:48.54" },
      "14":  { "OSC": "4:38.69", "OAG": "4:45.66" },
      "15":  { "OSC": "4:35.90", "OAG": "4:42.80" },
      "16":  { "OSC": "4:33.15", "OAG": "4:39.98" },
      "17O": { "OSC": "4:30.41", "OAG": "4:37.17" }
    },
    "800FR": {
      "11U": { "OSC": "10:50.25", "OAG": "11:06.51" },
      "12":  { "OSC": "10:25.17", "OAG": "10:40.80" },
      "13U": { "OSC": "9:47.87", "OAG": "10:02.57" },
      "14":  { "OSC": "9:41.99", "OAG": "9:56.54" },
      "15":  { "OSC": "9:36.17", "OAG": "9:50.57" },
      "16":  { "OSC": "9:30.40", "OAG": "9:44.66" },
      "17O": { "OSC": "9:24.70", "OAG": "9:38.82" }
    },
    "1500FR": {
      "11U": { "OSC": null, "OAG": null },
      "12":  { "OSC": null, "OAG": null },
      "13U": { "OSC": "19:00.19", "OAG": "19:28.69" },
      "14":  { "OSC": "18:48.78", "OAG": "19:17.00" },
      "15":  { "OSC": "18:37.50", "OAG": "19:05.44" },
      "16":  { "OSC": "18:26.32", "OAG": "18:53.98" },
      "17O": { "OSC": "18:15.26", "OAG": "18:42.64" }
    },
    "50BK": {
      "11U": { "OSC": "0:37.16", "OAG": "0:38.09" },
      "12":  { "OSC": "0:35.23", "OAG": "0:36.11" },
      "13U": { "OSC": "0:32.75", "OAG": "0:33.57" },
      "14":  { "OSC": "0:32.12", "OAG": "0:32.92" },
      "15":  { "OSC": "0:31.51", "OAG": "0:32.30" },
      "16":  { "OSC": "0:31.16", "OAG": "0:31.94" },
      "17O": { "OSC": "0:30.84", "OAG": "0:31.61" }
    },
    "100BK": {
      "11U": { "OSC": "1:19.09", "OAG": "1:21.07" },
      "12":  { "OSC": "1:16.02", "OAG": "1:17.92" },
      "13U": { "OSC": "1:10.57", "OAG": "1:12.33" },
      "14":  { "OSC": "1:09.86", "OAG": "1:11.61" },
      "15":  { "OSC": "1:08.84", "OAG": "1:10.56" },
      "16":  { "OSC": "1:07.44", "OAG": "1:09.13" },
      "17O": { "OSC": "1:06.66", "OAG": "1:08.33" }
    },
    "200BK": {
      "11U": { "OSC": "2:49.41", "OAG": "2:53.65" },
      "12":  { "OSC": "2:43.81", "OAG": "2:47.91" },
      "13U": { "OSC": "2:33.48", "OAG": "2:37.32" },
      "14":  { "OSC": "2:31.40", "OAG": "2:35.19" },
      "15":  { "OSC": "2:29.30", "OAG": "2:33.03" },
      "16":  { "OSC": "2:27.11", "OAG": "2:30.79" },
      "17O": { "OSC": "2:25.64", "OAG": "2:29.28" }
    },
    "50BR": {
      "11U": { "OSC": "0:42.00", "OAG": "0:43.05" },
      "12":  { "OSC": "0:39.47", "OAG": "0:40.46" },
      "13U": { "OSC": "0:35.86", "OAG": "0:36.76" },
      "14":  { "OSC": "0:35.50", "OAG": "0:36.39" },
      "15":  { "OSC": "0:35.15", "OAG": "0:36.03" },
      "16":  { "OSC": "0:34.79", "OAG": "0:35.66" },
      "17O": { "OSC": "0:34.45", "OAG": "0:35.31" }
    },
    "100BR": {
      "11U": { "OSC": "1:30.87", "OAG": "1:33.14" },
      "12":  { "OSC": "1:26.42", "OAG": "1:28.58" },
      "13U": { "OSC": "1:19.29", "OAG": "1:21.27" },
      "14":  { "OSC": "1:18.50", "OAG": "1:20.46" },
      "15":  { "OSC": "1:17.72", "OAG": "1:19.66" },
      "16":  { "OSC": "1:16.94", "OAG": "1:18.86" },
      "17O": { "OSC": "1:16.18", "OAG": "1:18.08" }
    },
    "200BR": {
      "11U": { "OSC": "3:14.11", "OAG": "3:18.96" },
      "12":  { "OSC": "3:05.26", "OAG": "3:09.89" },
      "13U": { "OSC": "2:53.68", "OAG": "2:58.02" },
      "14":  { "OSC": "2:51.94", "OAG": "2:56.24" },
      "15":  { "OSC": "2:50.23", "OAG": "2:54.49" },
      "16":  { "OSC": "2:48.52", "OAG": "2:52.73" },
      "17O": { "OSC": "2:46.83", "OAG": "2:51.00" }
    },
    "50FL": {
      "11U": { "OSC": "0:34.86", "OAG": "0:35.73" },
      "12":  { "OSC": "0:32.64", "OAG": "0:33.46" },
      "13U": { "OSC": "0:30.19", "OAG": "0:30.94" },
      "14":  { "OSC": "0:29.88", "OAG": "0:30.63" },
      "15":  { "OSC": "0:29.27", "OAG": "0:30.00" },
      "16":  { "OSC": "0:28.98", "OAG": "0:29.70" },
      "17O": { "OSC": "0:28.63", "OAG": "0:29.35" }
    },
    "100FL": {
      "11U": { "OSC": "1:19.62", "OAG": "1:21.61" },
      "12":  { "OSC": "1:14.99", "OAG": "1:16.86" },
      "13U": { "OSC": "1:08.37", "OAG": "1:10.08" },
      "14":  { "OSC": "1:07.69", "OAG": "1:09.38" },
      "15":  { "OSC": "1:06.55", "OAG": "1:08.21" },
      "16":  { "OSC": "1:05.74", "OAG": "1:07.38" },
      "17O": { "OSC": "1:05.00", "OAG": "1:06.63" }
    },
    "200FL": {
      "11U": { "OSC": "3:13.77", "OAG": "3:18.61" },
      "12":  { "OSC": "2:56.65", "OAG": "3:01.07" },
      "13U": { "OSC": "2:37.08", "OAG": "2:41.01" },
      "14":  { "OSC": "2:35.51", "OAG": "2:39.40" },
      "15":  { "OSC": "2:33.95", "OAG": "2:37.80" },
      "16":  { "OSC": "2:32.04", "OAG": "2:35.84" },
      "17O": { "OSC": "2:30.52", "OAG": "2:34.28" }
    },
    "200IM": {
      "11U": { "OSC": "2:50.20", "OAG": "2:54.46" },
      "12":  { "OSC": "2:44.06", "OAG": "2:48.16" },
      "13U": { "OSC": "2:33.62", "OAG": "2:37.46" },
      "14":  { "OSC": "2:31.58", "OAG": "2:35.37" },
      "15":  { "OSC": "2:30.06", "OAG": "2:33.81" },
      "16":  { "OSC": "2:27.74", "OAG": "2:31.43" },
      "17O": { "OSC": "2:26.25", "OAG": "2:29.91" }
    },
    "400IM": {
      "11U": { "OSC": "6:00.43", "OAG": "6:09.44" },
      "12":  { "OSC": "5:47.05", "OAG": "5:55.73" },
      "13U": { "OSC": "5:24.40", "OAG": "5:32.51" },
      "14":  { "OSC": "5:21.16", "OAG": "5:29.19" },
      "15":  { "OSC": "5:17.94", "OAG": "5:25.89" },
      "16":  { "OSC": "5:14.76", "OAG": "5:22.63" },
      "17O": { "OSC": "5:11.62", "OAG": "5:19.41" }
    }
  }
}
